excprocess/__init__.py
excprocess/exceptions.py
excprocess-0.1.2.dist-info/WHEEL
excprocess-0.1.2.dist-info/METADATA
excprocess-0.1.2.dist-info/RECORD
